greytheory/__init__.py
greytheory/example.py
greytheory/packages/__init__.py
greytheory/packages/libs/__init__.py
greytheory/packages/libs/grey_lib.py
greytheory/packages/libs/grey_math.py
greytheory/packages/models/__init__.py
greytheory/packages/models/grey_class.py
greytheory/packages/models/grey_factory.py
greytheory/packages/models/grey_forecast.py
greytheory/packages/models/grey_gm0n.py
greytheory/packages/models/grey_gm11.py
greytheory/packages/models/grey_gm1n.py
greytheory/packages/models/grey_run.py
greytheory-0.1.dist-info/METADATA
greytheory-0.1.dist-info/RECORD
greytheory-0.1.dist-info/WHEEL
greytheory-0.1.dist-info/top_level.txt
