Metadata-Version: 2.1
Name: greytheory
Version: 0.1
Summary: Grey theory, implemented by python.
Home-page: https://github.com/Kalvar/python-GreyTheory.git
Author: Kalvar
Author-email: ilovekalvar@gmail.com
License: UNKNOWN
Platform: UNKNOWN
Classifier: Development Status :: 5 - Production/Stable
Classifier: Programming Language :: Python :: 3
Classifier: License :: OSI Approved :: MIT License
Classifier: Operating System :: OS Independent
Requires-Python: >=3.6
